README.md
affirmative_sampling/__init__.py
affirmative_sampling/algorithm.py
affirmative_sampling/example.py
affirmative_sampling-1.0.0.dist-info/LICENSE
affirmative_sampling-1.0.0.dist-info/WHEEL
affirmative_sampling-1.0.0.dist-info/METADATA
affirmative_sampling-1.0.0.dist-info/RECORD
