Metadata-Version: 2.1
Name: affirmative-sampling
Version: 1.0.0
Summary: Reference implementation of the Affirmative Sampling algorithm by Jérémie Lumbroso and Conrado Martínez (2022).
Home-page: https://github.com/jlumbroso/affirmative-sampling
License: LGPL-3.0-or-later
Author: Jérémie Lumbroso
Author-email: lumbroso@cs.princeton.edu
Requires-Python: >=3.8,<4.0
Classifier: Development Status :: 4 - Beta
Classifier: License :: OSI Approved :: GNU Lesser General Public License v3 or later (LGPLv3+)
Classifier: Programming Language :: Python :: 3
Classifier: Programming Language :: Python :: 3.10
Classifier: Programming Language :: Python :: 3.8
Classifier: Programming Language :: Python :: 3.9
Classifier: Topic :: Software Development :: Libraries :: Python Modules
Requires-Dist: randomhash (>=0.6.0,<0.7.0)
Requires-Dist: requests (>=2.27.1,<3.0.0)
Project-URL: Repository, https://github.com/jlumbroso/affirmative-sampling
